odoo/addons/website_snippet_country_phone_code_dropdown/README.rst
odoo/addons/website_snippet_country_phone_code_dropdown/__init__.py
odoo/addons/website_snippet_country_phone_code_dropdown/__manifest__.py
odoo/addons/website_snippet_country_phone_code_dropdown/demo/pages.xml
odoo/addons/website_snippet_country_phone_code_dropdown/i18n/it.po
odoo/addons/website_snippet_country_phone_code_dropdown/i18n/website_snippet_country_phone_code_dropdown.pot
odoo/addons/website_snippet_country_phone_code_dropdown/readme/CONTRIBUTORS.rst
odoo/addons/website_snippet_country_phone_code_dropdown/readme/DESCRIPTION.rst
odoo/addons/website_snippet_country_phone_code_dropdown/readme/USAGE.rst
odoo/addons/website_snippet_country_phone_code_dropdown/static/description/icon.png
odoo/addons/website_snippet_country_phone_code_dropdown/static/description/index.html
odoo/addons/website_snippet_country_phone_code_dropdown/static/src/css/style.scss
odoo/addons/website_snippet_country_phone_code_dropdown/static/src/js/web_tour_country_phone_code_dropdown.js
odoo/addons/website_snippet_country_phone_code_dropdown/static/src/js/website_snippet_country_phone_code_dropdown.js
odoo/addons/website_snippet_country_phone_code_dropdown/tests/__init__.py
odoo/addons/website_snippet_country_phone_code_dropdown/tests/test_snippet_country_phone_code_dropdown.py
odoo/addons/website_snippet_country_phone_code_dropdown/views/snippets.xml
odoo_addon_website_snippet_country_phone_code_dropdown-16.0.1.0.0.3.dist-info/METADATA
odoo_addon_website_snippet_country_phone_code_dropdown-16.0.1.0.0.3.dist-info/WHEEL
odoo_addon_website_snippet_country_phone_code_dropdown-16.0.1.0.0.3.dist-info/top_level.txt
odoo_addon_website_snippet_country_phone_code_dropdown-16.0.1.0.0.3.dist-info/RECORD
