Metadata-Version: 2.1
Name: odoo-addon-website_snippet_country_phone_code_dropdown
Version: 16.0.1.0.0.3
Summary: Allow to select country in a dropdown, and fill with phone code
Home-page: https://github.com/OCA/website
Author: ForgeFlow, Odoo Community Association (OCA)
Author-email: support@odoo-community.org
License: LGPL-3
Classifier: Programming Language :: Python
Classifier: Framework :: Odoo
Classifier: Framework :: Odoo :: 16.0
Classifier: License :: OSI Approved :: GNU Lesser General Public License v3 (LGPLv3)
Requires-Python: >=3.10
Requires-Dist: odoo-addon-website-snippet-country-dropdown<16.1dev,>=16.0dev
Requires-Dist: odoo<16.1dev,>=16.0a
